LICENSE
MANIFEST.in
README.md
setup.py
docs/CONTRIBUTING.md
docs/index.rst
docs/reticle.aws.batch.rst
docs/reticle.aws.exception.rst
docs/reticle.aws.logs.rst
docs/reticle.aws.response.rst
docs/reticle.aws.rst
docs/reticle.aws.s3.rst
docs/reticle.rst
docs/reticle.util.rst
reticle/__init__.py
reticle/util.py
reticle.egg-info/PKG-INFO
reticle.egg-info/SOURCES.txt
reticle.egg-info/dependency_links.txt
reticle.egg-info/not-zip-safe
reticle.egg-info/requires.txt
reticle.egg-info/top_level.txt