Metadata-Version: 2.1
Name: reticle
Version: 0.1.0
Summary: Python 3.6+ library for submitting to AWS Batch interactively.
Home-page: https://github.com/clintval/reticle
Author: clintval
Author-email: valentine.clint@gmail.com
License: MIT
Download-URL: https://github.com/clintval/reticle/archive/v0.1.0.tar.gz
Project-URL: Documentation, https://reticle.readthedocs.io
Project-URL: Issue-Tracker, https://github.com/clintval/reticle/issues
Keywords: AWS Batch job submission
Platform: UNKNOWN
Classifier: Development Status :: 2 - Pre-Alpha
Classifier: Intended Audience :: Developers
Classifier: License :: OSI Approved :: MIT License
Classifier: Programming Language :: Python :: 3.6
Classifier: Programming Language :: Python :: 3.7
